[{"id":167,"name":"Dhaka","nameBn":"ঢাকা"},{"id":168,"name":"Faridpur","nameBn":"ফরিদপুর"},{"id":169,"name":"Gazipur","nameBn":"গাজীপুর"},{"id":170,"name":"Gopalganj","nameBn":"গোপালগঞ্জ"},{"id":171,"name":"Kishoreganj","nameBn":"কিশোরগঞ্জ"},{"id":172,"name":"Madaripur","nameBn":"মাদারীপুর"},{"id":173,"name":"Manikganj","nameBn":"মানিকগঞ্জ"},{"id":174,"name":"Munshiganj","nameBn":"মুন্সীগঞ্জ"},{"id":175,"name":"Narayanganj","nameBn":"নারায়ণগঞ্জ"},{"id":176,"name":"Rajbari","nameBn":"রাজবাড়ী"},{"id":177,"name":"Shariatpur","nameBn":"শরীয়তপুর"},{"id":178,"name":"Tangail","nameBn":"টাঙ্গাইল"},{"id":179,"name":"Narsingdi","nameBn":"নরসিংদী"}]